segyviewlib/LICENSE
segyviewlib/__init__.py
segyviewlib/_indexcontroller.py
segyviewlib/_plotexportsettingscontroller.py
segyviewlib/_samplescalecontroller.py
segyviewlib/arrayspinbox.py
segyviewlib/colormapcombo.py
segyviewlib/helpwindow.py
segyviewlib/layoutcanvas.py
segyviewlib/layoutcombo.py
segyviewlib/layoutfigure.py
segyviewlib/segyviewwidget.py
segyviewlib/segywidgetcollection.py
segyviewlib/settingswindow.py
segyviewlib/slicedatasource.py
segyviewlib/slicemodel.py
segyviewlib/sliceview.py
segyviewlib/sliceviewcontext.py
segyviewlib/sliceviewwidget.py
segyviewlib/version.py
segyviewlib/resources/img/350px-SEGYIO.png
segyviewlib/resources/img/cog.png
segyviewlib/resources/img/folder.png
segyviewlib/resources/img/layouts_four_grid.png
segyviewlib/resources/img/layouts_single.png
segyviewlib/resources/img/layouts_three_bottom_grid.png
segyviewlib/resources/img/layouts_three_horizontal_grid.png
segyviewlib/resources/img/layouts_three_left_grid.png
segyviewlib/resources/img/layouts_three_right_grid.png
segyviewlib/resources/img/layouts_three_top_grid.png
segyviewlib/resources/img/layouts_three_vertical_grid.png
segyviewlib/resources/img/layouts_two_horizontal_grid.png
segyviewlib/resources/img/layouts_two_vertical_grid.png
segyviewlib/resources/img/readme.txt
segyviewlib/resources/img/table_export.png
segyviewlib-1.1.3.dist-info/LICENSE
segyviewlib-1.1.3.dist-info/METADATA
segyviewlib-1.1.3.dist-info/WHEEL
segyviewlib-1.1.3.dist-info/top_level.txt
segyviewlib-1.1.3.dist-info/RECORD
